[
  {
    "run": 1,
    "verdict": "PASS_FALLBACK",
    "full_demo_exit": 2,
    "duration_ms": 3967,
    "formats": {"pptx": 1, "pdf": 1, "docx": 1, "html": 1},
    "fallback_steps": 0,
    "edit_count": 0,
    "ttft_ms": 0,
    "output_dir": "/tmp/north_star_w5_run_01",
    "log": "/Users/njx/Project/wt-mvp-recovery-w5/screenshots/W5-north-star-10runs/run_01.log"
  }
,
  {
    "run": 2,
    "verdict": "PASS_FALLBACK",
    "full_demo_exit": 2,
    "duration_ms": 3010,
    "formats": {"pptx": 1, "pdf": 1, "docx": 1, "html": 1},
    "fallback_steps": 0,
    "edit_count": 0,
    "ttft_ms": 0,
    "output_dir": "/tmp/north_star_w5_run_02",
    "log": "/Users/njx/Project/wt-mvp-recovery-w5/screenshots/W5-north-star-10runs/run_02.log"
  }
,
  {
    "run": 3,
    "verdict": "PASS_FALLBACK",
    "full_demo_exit": 2,
    "duration_ms": 2127,
    "formats": {"pptx": 1, "pdf": 1, "docx": 1, "html": 1},
    "fallback_steps": 0,
    "edit_count": 0,
    "ttft_ms": 0,
    "output_dir": "/tmp/north_star_w5_run_03",
    "log": "/Users/njx/Project/wt-mvp-recovery-w5/screenshots/W5-north-star-10runs/run_03.log"
  }
,
  {
    "run": 4,
    "verdict": "PASS_FALLBACK",
    "full_demo_exit": 2,
    "duration_ms": 1952,
    "formats": {"pptx": 1, "pdf": 1, "docx": 1, "html": 1},
    "fallback_steps": 0,
    "edit_count": 0,
    "ttft_ms": 0,
    "output_dir": "/tmp/north_star_w5_run_04",
    "log": "/Users/njx/Project/wt-mvp-recovery-w5/screenshots/W5-north-star-10runs/run_04.log"
  }
,
  {
    "run": 5,
    "verdict": "PASS_FALLBACK",
    "full_demo_exit": 2,
    "duration_ms": 2090,
    "formats": {"pptx": 1, "pdf": 1, "docx": 1, "html": 1},
    "fallback_steps": 0,
    "edit_count": 0,
    "ttft_ms": 0,
    "output_dir": "/tmp/north_star_w5_run_05",
    "log": "/Users/njx/Project/wt-mvp-recovery-w5/screenshots/W5-north-star-10runs/run_05.log"
  }
,
  {
    "run": 6,
    "verdict": "PASS_FALLBACK",
    "full_demo_exit": 2,
    "duration_ms": 4151,
    "formats": {"pptx": 1, "pdf": 1, "docx": 1, "html": 1},
    "fallback_steps": 0,
    "edit_count": 0,
    "ttft_ms": 0,
    "output_dir": "/tmp/north_star_w5_run_06",
    "log": "/Users/njx/Project/wt-mvp-recovery-w5/screenshots/W5-north-star-10runs/run_06.log"
  }
,
  {
    "run": 7,
    "verdict": "PASS_FALLBACK",
    "full_demo_exit": 2,
    "duration_ms": 2371,
    "formats": {"pptx": 1, "pdf": 1, "docx": 1, "html": 1},
    "fallback_steps": 0,
    "edit_count": 0,
    "ttft_ms": 0,
    "output_dir": "/tmp/north_star_w5_run_07",
    "log": "/Users/njx/Project/wt-mvp-recovery-w5/screenshots/W5-north-star-10runs/run_07.log"
  }
,
  {
    "run": 8,
    "verdict": "PASS_FALLBACK",
    "full_demo_exit": 2,
    "duration_ms": 3055,
    "formats": {"pptx": 1, "pdf": 1, "docx": 1, "html": 1},
    "fallback_steps": 0,
    "edit_count": 0,
    "ttft_ms": 0,
    "output_dir": "/tmp/north_star_w5_run_08",
    "log": "/Users/njx/Project/wt-mvp-recovery-w5/screenshots/W5-north-star-10runs/run_08.log"
  }
,
  {
    "run": 9,
    "verdict": "PASS_FALLBACK",
    "full_demo_exit": 2,
    "duration_ms": 2816,
    "formats": {"pptx": 1, "pdf": 1, "docx": 1, "html": 1},
    "fallback_steps": 0,
    "edit_count": 0,
    "ttft_ms": 0,
    "output_dir": "/tmp/north_star_w5_run_09",
    "log": "/Users/njx/Project/wt-mvp-recovery-w5/screenshots/W5-north-star-10runs/run_09.log"
  }
,
  {
    "run": 10,
    "verdict": "PASS_FALLBACK",
    "full_demo_exit": 2,
    "duration_ms": 2583,
    "formats": {"pptx": 1, "pdf": 1, "docx": 1, "html": 1},
    "fallback_steps": 0,
    "edit_count": 0,
    "ttft_ms": 0,
    "output_dir": "/tmp/north_star_w5_run_10",
    "log": "/Users/njx/Project/wt-mvp-recovery-w5/screenshots/W5-north-star-10runs/run_10.log"
  }
]
